RTL/Clockworks.v
module Clockworks (
    input  CLK,
    input  RESET,
    output clk,
    output resetn
);
    parameter SLOW = 21;

    // Clock divider
    reg [SLOW:0] slow_CLK = 0;
    always @(posedge CLK) begin
        if (!RESET)
            slow_CLK <= 0;
        else
            slow_CLK <= slow_CLK + 1;

    end
    assign clk = slow_CLK[SLOW];
    assign resetn = RESET;


endmodule

RTL/SOC.v
`default_nettype none
`include "Clockworks.v"

module SOC(
    input CLK,
    input RESET,
    output [4:0] LEDS,
    input RXD,
    output TXD
);

    Clockworks #(
      .SLOW(2) // Divide clock frequency by 2^21
   )CW(
     .CLK(CLK),
     .RESET(RESET),

     .clk(clk),
     .resetn(resetn)
   );

    wire clk;
    wire resetn;

    reg[31:0] MEM [0:255];
    reg[31:0] PC;

    reg[31:0] instr;

   
    // opcodes for instruction type
    wire R_type = (instr[6:0] == 7'b0110011);
    wire I_type = (instr[6:0] == 7'b0010011);
    wire B_type = (instr[6:0] == 7'b1100011);
    wire JALR   = (instr[6:0] == 7'b1100111);
    wire JAL    = (instr[6:0] == 7'b1101111);

    wire AUIPC  = (instr[6:0] == 7'b0010111); 
    wire LUI    = (instr[6:0] == 7'b0110111);
    wire Load   = (instr[6:0] == 7'b0000011);
    wire Store  = (instr[6:0] == 7'b0100011);
    wire SYSTEM = (instr[6:0] == 7'b1110011);


    // rtype decode
    wire [4:0]rs2 = instr[24:20];
    wire [4:0]rs1 = instr[19:15];
    wire [4:0]rd  = instr[11:7];

    wire [6:0]funct7 = instr[31:25];
    wire [2:0]funct3 = instr[14:12];

    // itype decode

    // sign extended
    wire [31:0]Iimm = {{21{instr[31]}}, instr[30:20]};

    // store
    wire [31:0]Simm = {{21{instr[31]}}, instr[30:25], instr[11:7]};

    // btype
    wire [31:0]Bimm = {{20{instr[31]}}, instr[7], instr[30:25], instr[11:8], 1'b0};


    // utype
    wire [31:0]Uimm = {instr[31], instr[30:12], {12{1'b0}}};   

    // jtype
  	wire [31:0]Jimm = {{12{instr[31]}}, instr[19:12], instr[20], instr[30:21], 1'b0};


    initial begin
        PC = 0;


        // add x0, x0, x0
        //                   rs2   rs1  add  rd   ALUREG

        instr = 32'b0000000_00000_00000_000_00000_0110011;

        // add x1, x0, x0
        //                    rs2   rs1  add  rd  ALUREG
        MEM[0] = 32'b0000000_00000_00000_000_00001_0110011;


        // addi x1, x1, 1
        //             imm         rs1  add  rd   ALUIMM

        MEM[1] = 32'b000000000001_00001_000_00001_0010011;

        // addi x1, x1, 1
        //             imm         rs1  add  rd   ALUIMM
        MEM[2] = 32'b000000000001_00001_000_00001_0010011;


        // addi x1, x1, 1
        //             imm         rs1  add  rd   ALUIMM

        MEM[3] = 32'b000000000001_00001_000_00001_0010011;

        // addi x1, x1, 1
        //             imm         rs1  add  rd   ALUIMM
        MEM[4] = 32'b000000000001_00001_000_00001_0010011;


        // lw x2,0(x1)
        //             imm         rs1   w   rd   LOAD
        MEM[5] = 32'b000000000000_00001_010_00010_0000011;

        // sw x2,0(x1)
        //             imm   rs2   rs1   w   imm  STORE
        MEM[6] = 32'b000000_00001_00010_010_00000_0100011;

        // ebreak

        //                                        SYSTEM
        MEM[7] = 32'b000000000001_00000_000_00000_1110011;

    end

    always @(posedge clk) begin
        if(!resetn)
            PC <= 0;
        else if(!SYSTEM) begin
            instr <= MEM[PC];
            PC <= PC+1;
        end
        `ifdef bench      
            if(SYSTEM) $finish();
        `endif 
    end

    assign LEDS = SYSTEM ? 31 : {PC[0],R_type,I_type,Store,Load};

    `ifdef bench   
    always @(posedge clk) begin
        $display("PC=%0d",PC);
        case (1'b1)
        R_type: $display(
            "ALUreg rd=%d rs1=%d rs2=%d funct3=%b",
                rd, rs1, rs2, funct3
            );
        I_type: $display(
            "ALUimm rd=%d rs1=%d imm=%0d funct3=%b",
                rd, rs1, Iimm, funct3
            );
        B_type: $display("BRANCH");
        JAL:    $display("JAL");
        JALR:   $display("JALR");
        AUIPC:  $display("AUIPC");
        LUI:    $display("LUI");	
        Load:   $display("LOAD");
        Store:  $display("STORE");
        SYSTEM: $display("SYSTEM");
        endcase 
    end
`endif
    assign TXD = 1'b0; 
endmodule

RTL/bench.sv
module bench();
   reg CLK;
   reg RESET = 0;
   wire [4:0] LEDS;
   reg  RXD = 1'b0;
   wire TXD;

   SOC uut(
     .CLK(CLK),
     .RESET(RESET),
     .LEDS(LEDS)
   );


  reg[4:0] prev_LEDS = 0;
  //initial #500 $finish;
   initial begin
      RESET = 1;
      CLK = 0;
      forever begin

	 #1 CLK = ~CLK;
	 if(LEDS != prev_LEDS) begin
	    $display("LEDS = %b",LEDS);

	 end
	 prev_LEDS <= LEDS;
      end
   end

  initial begin
    $dumpfile("sim.vcd");
    $dumpvars(0, bench);
  end
  
endmodule

RTL/sim.vcd
$date
	Thu Mar 19 23:27:37 2026
$end
$version
	Icarus Verilog
$end
$timescale
	1s
$end
$scope module bench $end
$var wire 5 ! LEDS [4:0] $end
$var reg 1 " CLK $end
$var reg 1 # RESET $end
$var reg 1 $ RXD $end
$var reg 5 % prev_LEDS [4:0] $end
$scope module uut $end
$var wire 1 " CLK $end
$var wire 1 # RESET $end
$var wire 1 & RXD $end
$var wire 1 ' TXD $end
$var wire 5 ( rs2 [4:0] $end
$var wire 5 ) rs1 [4:0] $end
$var wire 1 * resetn $end
$var wire 5 + rd [4:0] $end
$var wire 7 , funct7 [6:0] $end
$var wire 3 - funct3 [2:0] $end
$var wire 1 . clk $end
$var wire 32 / Uimm [31:0] $end
$var wire 1 0 Store $end
$var wire 32 1 Simm [31:0] $end
$var wire 1 2 SYSTEM $end
$var wire 1 3 R_type $end
$var wire 1 4 Load $end
$var wire 1 5 LUI $end
$var wire 5 6 LEDS [4:0] $end
$var wire 32 7 Jimm [31:0] $end
$var wire 1 8 JALR $end
$var wire 1 9 JAL $end
$var wire 32 : Iimm [31:0] $end
$var wire 1 ; I_type $end
$var wire 32 < Bimm [31:0] $end
$var wire 1 = B_type $end
$var wire 1 > AUIPC $end
$var reg 32 ? PC [31:0] $end
$var reg 32 @ instr [31:0] $end
$scope module CW $end
$var wire 1 " CLK $end
$var wire 1 # RESET $end
$var wire 1 * resetn $end
$var wire 1 . clk $end
$var parameter 32 A SLOW $end
$var reg 3 B slow_CLK [2:0] $end
$upscope $end
$upscope $end
$upscope $end
$enddefinitions $end
$comment Show the parameter values. $end
$dumpall
b10 A
$end
#0
$dumpvars
b0 B
b110011 @
b0 ?
0>
0=
b0 <
0;
b0 :
09
08
b0 7
b1000 6
05
04
13
02
b0 1
00
b0 /
0.
b0 -
b0 ,
b0 +
1*
b0 )
b0 (
0'
z&
b0 %
0$
1#
0"
b1000 !
$end
#1
b1 B
b1000 %
1"
#2
0"
#3
b10 B
1"
#4
0"
#5
b11 B
1"
#6
0"
#7
b11000 !
b11000 6
b1 +
b1 1
b100000000000 <
b1 ?
b10110011 @
1.
b100 B
1"
#8
b11000 %
0"
#9
b101 B
1"
#10
0"
#11
b110 B
1"
#12
0"
#13
b111 B
1"
#14
0"
#15
0.
b0 B
1"
#16
0"
#17
b1 B
1"
#18
0"
#19
b10 B
1"
#20
0"
#21
b11 B
1"
#22
0"
#23
b100 !
b100 6
03
1;
b1 (
b1 )
b1 :
b100001000000000000000 /
b1000100000000000 7
b10 ?
b100001000000010010011 @
1.
b100 B
1"
#24
b100 %
0"
#25
b101 B
1"
#26
0"
#27
b110 B
1"
#28
0"
#29
b111 B
1"
#30
0"
#31
0.
b0 B
1"
#32
0"
#33
b1 B
1"
#34
0"
#35
b10 B
1"
#36
0"
#37
b11 B
1"
#38
0"
#39
b10100 !
b10100 6
b11 ?
1.
b100 B
1"
#40
b10100 %
0"
#41
b101 B
1"
#42
0"
#43
b110 B
1"
#44
0"
#45
b111 B
1"
#46
0"
#47
0.
b0 B
1"
#48
0"
#49
b1 B
1"
#50
0"
#51
b10 B
1"
#52
0"
#53
b11 B
1"
#54
0"
#55
b100 !
b100 6
b100 ?
1.
b100 B
1"
#56
b100 %
0"
#57
b101 B
1"
#58
0"
#59
b110 B
1"
#60
0"
#61
b111 B
1"
#62
0"
#63
0.
b0 B
1"
#64
0"
#65
b1 B
1"
#66
0"
#67
b10 B
1"
#68
0"
#69
b11 B
1"
#70
0"
#71
b10100 !
b10100 6
b101 ?
1.
b100 B
1"
#72
b10100 %
0"
#73
b101 B
1"
#74
0"
#75
b110 B
1"
#76
0"
#77
b111 B
1"
#78
0"
#79
0.
b0 B
1"
#80
0"
#81
b1 B
1"
#82
0"
#83
b10 B
1"
#84
0"
#85
b11 B
1"
#86
0"
#87
b1 !
b1 6
0;
14
b0 (
b10 +
b10 -
b0 :
b10 1
b10 <
b1010000000000000 /
b1010000000000000 7
b110 ?
b1010000100000011 @
1.
b100 B
1"
#88
b1 %
0"
#89
b101 B
1"
#90
0"
#91
b110 B
1"
#92
0"
#93
b111 B
1"
#94
0"
#95
0.
b0 B
1"
#96
0"
#97
b1 B
1"
#98
0"
#99
b10 B
1"
#100
0"
#101
b11 B
1"
#102
0"
#103
b10010 !
b10010 6
04
10
b1 (
b10 )
b0 +
b1 :
b0 1
b0 <
b100010010000000000000 /
b10010100000000000 7
b111 ?
b100010010000000100011 @
1.
b100 B
1"
#104
b10010 %
0"
#105
b101 B
1"
#106
0"
#107
b110 B
1"
#108
0"
#109
b111 B
1"
#110
0"
#111
0.
b0 B
1"
#112
0"
#113
b1 B
1"
#114
0"
#115
b10 B
1"
#116
0"
#117
b11 B
1"
#118
0"
#119
b11111 !
b11111 6
00
12
b0 )
b0 -
b100000000000000000000 /
b100000000000 7
b1000 ?
b100000000000001110011 @
1.
b100 B
1"
#120
b11111 %
0"
#121
b101 B
1"
#122
0"
#123
b110 B
1"
#124
0"
#125
b111 B
1"
#126
0"
#127
0.
b0 B
1"
#128
0"
#129
b1 B
1"
#130
0"
#131
b10 B
1"
#132
0"
#133
b11 B
1"
#134
0"
#135
1.
b100 B
1"
